{
  "task": "Fix remaining Flutter test compilation/runtime failures and run all tests",
  "steps": [
    "Fix auth_bloc.dart compilation errors (nullable UserRepository issue)",
    "Fix login_page_test.dart widget failures (viewport/scrolling/tab issues)",
    "Fix cart_bloc_test.dart any remaining issues",
    "Run flutter test -- all tests passing",
    "Update coverage/bug registry docs"
  ],
  "status": "ALL TESTS PASSING",
  "backend_tests": "77/77 passing (JaCoCo executed)",
  "flutter_tests": "133/133 passing",
  "grand_total": "210/210 passing",
  "last_verified": "2026-05-11"
}
